ATL_Tools/ATL_gdal.py
ATL_Tools/ATL_path.py
ATL_Tools/__init__.py
atl_tools-1.3.0.dist-info/METADATA
atl_tools-1.3.0.dist-info/WHEEL
atl_tools-1.3.0.dist-info/top_level.txt
atl_tools-1.3.0.dist-info/RECORD
