Metadata-Version: 2.4
Name: ATL_Tools
Version: 1.3.0
Summary: AI-Tianlong的Tools打包，开箱即用, 包含ATL_path和ATL_gdal,可用于文件夹创建、文件搜索、遥感图像处理
License: MIT License
Keywords: ATL_Tools,GDAL,AI-Tianlong,Chinese
